 [{
         "client": {
             "company":{
                "fm_company_id": "0001",
                "fm_company_name": "Merck",
                "fm_region_list": {
                    "EU": "Europe",
                    "AF": "Africa",
                    "AS": "Asia"
                },
                "fm_country_list": {
                    "FR": "France",
                    "GB": "United Kingdom",
                    "BE": "Belgium"
                },// Attention a complêter
                "fm_bu_list": {
                    "DIA": "Diabete",
                    "CAR": "Cardiovascular",
                    "OTC": "OTC",
                    "PAI": "Pain"
                },
                "fm_fm_access_date": "2017/10/01 18:03:07 GMT+0200",
                "fm_sm_access_date": "2017/10/01 19:03:07 GMT+0200",
                "fm_product_list": {
                    "COM": "Comigral",
                    "MAV": "Mavencad",
                    "REB": "Rebif",
                    "GLU": "Glucophage",
                    "JAN": "Januvia"
                    "LEV": "Levothyrox"
                },
                "fm_category_list": {
                   "cat1": "efficacy",
                   "cat2": "posologie",
                   "cat3": "epidemilogie" // a completer tous les cat de la compagnie
                }
                "fm_specialty_list": {
                   "cat1": "General Practitioner",
                   "cat2": "posologie",
                   "cat3": "epidemilogie" // a completer tous les cat de la compagnie
                }
             },
             "user":{
                "fm_user_id": "4",
                "fm_user_name": "julien.meichler",
                "fm_firstname": "julien",
                "fm_lastname": "meichler",
                "fm_mail": "julien.meichler@hubdata.fr",
                "fm_account_type": "ADMIN",
                "fm_spoken_language": "FR",
                "fm_position_name": "PM",
                "fm_user_country": "FR"
             }
         },
         "project": {
             "fm_project_id": "ud41d8cd98f00b204e9800998ecf8427e",
             "fm_create_date": "2017/10/04 18:03:07 GMT+0200",
             "fm_project_product_id": "COM",
             "fm_project_product_name": "COMIGRAL",
             "fm_project_bu_id": "OTC",
             "fm_project_bu_name": "Pain"
             "fm_project_country_id": "FR",
             "fm_project_country_name": "France",
             "fm_campaign_id": "74c335b723c7e157cc1fabd8f0ab128d",
             "fm_camapaign_name":"OTC basket promotion 2017",
             "fm_source": "FM",
             "fm_authorized_users":["4","2", "1"],
             "clm_id": null ,
             "clm_name": null ,
             "presentation": {
                 "fm_presentation_id": "82d06bea0055b2cf1e2a009596e48f2f",
                 "fm_presentation_spoken_language": "FR",
                 "fm_presentation_channel": "EDE",
                 "fm_presentation_reps_team_configuration": {
                      "fm_reps_team_name" : null, 
                      "fm_product_portfolio": ['COM','MAV','REB'],
                      "fm_product_position": {
                          "P1": "COM" , "P2":"MAV","P3":"REB"
                      },
                      "fm_reps_quantity": 10,
                      "fm_average_call_day": 9,
                      "fm_visited_hcp_id": ["Cardiologue", "Diabetologue"] // a completer tous les cat de la compagnie
                 },
                 "fm_presentation_origin": "NEW",
                 "fm_presentation_name": "1709_MER_FR_OTC_COM",
                 "fm_presentation_deployement_date": "2017/11/01 18:03:07 GMT+0200",
                 "fm_presentation_expiration_date": "2018/10/04 18:03:07 GMT+0200",
                 "fm_presentation_approval_code": null,
                 "fm_presentation_custom_name": "Comigral flow introduction",
                 "fm_presentation_product_id": "COM",
                 "fm_presentation_product_name": "Comigral",
                 "fm_presentation_bu_id": "OTC",
                 "fm_presentation_bu_name": "Pain"
                 "fm_presentation_crm_id": "MI",
                 "fm_presentation_crm_name": "MI",
                 "fm_presentation_export_type": "MONO",
                 "fm_presentation_device_id": "IP",
                 "fm_presentation_device_name": "Ipad",
                 "fm_presentation_custom_marketer_message": "Good luck with this presentation fill free to check your reps speech in the training functionality.",
                 "fm_presentation_smpc": ["apidra_500_smpc.pdf", "apidra_600_smpc.pdf"],
                 "clm_presentation_id": null,
                 "clm_presentation_name": null,
                 "fm_version": {
                     "fm_version_id": "e1a9b2ffbaefd408da31159dec83166d",
                     "fm_version_generate_date": "2018/10/04 18:03:07 GMT+0200",
                     "fm_version_export_date": "2018/10/04 18:04:07 GMT+0200",
                     "fm_version_flow_count": "1",
                     "fm_sm_lcr_active": true,
                     "fm_sm_update": true
                 },
                 "crm_mv_survey": []
             },
             "sequence": [{
                 "fm_sequence_id": "0f731cba139ccc3dc3871ba21c82ba37",
                 "fm_sequence_name": "1709_MER_FR_OTC_COM_1507131656",
                 "fm_sequence_version": "0c3d1c61871e9cb83cbbe2d1979866c4",
                 "fm_sequence_is_shared": false,
                 "flows": [{
                     "id": "flow1",
                     "custom_name": null,
                     "product_id": ["COM"],
                     "marketers_custom_message": null,
                     "screen": [{
                         "fm_screen_id": "uniq id",// a continuer
                         "fm_origin_version": "refer to origin version ID",
                         "fm_screen_name": "Study schmurtz conclusion",
                         "fm_refer_to": "1_10.00",
                         "fm_position_id": "1_10.10",
                         "fm_level_importance":"MUST,HIGH,STANDARD,LOW",
                         "fm_chapter": null,
                         "fm_sub_chapter": null,
                         "fm_thumbnail": "image base64",
                         "fm_datatrackname": null,
                         "fm_category": null,
                         "fm_key_message": null,
                         "fm_objective": null,
                         "fm_selling_steps": null,
                         "fm_custom_data": null,
                         "fm_product": "prod1",
                         "fm_reps_speech": "On this screen please insist on the under diagnosed situation",
                         "fm_popup": [{
                                 "fm_name": "poup_name_1",
                                 "fm_category": "cat1",
                                 "custom_message": "freetext"
                             },
                             {
                                 "fm_name": "poup_name_2",
                                 "fm_category": "cat1",
                                 "custom_message": "freetext"
                             }
                         ],
                         "fm_flip_flap":[{
                               "fm_flip_name": "flip_name",
                               "fm_flip_category": "cat2",
                               "fm_flip_custom_message": "freetext",
                               "fm_flap_name": "flip_name",
                               "fm_flap_category": "cat3",
                               "fm_flap_custom_message": "freetext"
                         }],
                         "fm_pdf": [{
                             "fm_name": null
                         }],
                         "fm_reference": true,
                         "fm_video": [{
                             "fm_name": null,
                             "fm_total_duration": null
                         }],
                         "fm_tap_animation": [{
                             "fm_name": null
                         }]
                     }]
                 }]
             }],
             "flows":{
                  "flow1": ["fm_screen_id","fm_screen_id"]
             },
             "last_call_report": {
                 "general_settings":{
                      "module_lcr": "ON or OFF",
                      "survey_module": "ON or OFF",
                      "survey_copy_in_crm": "ON or OFF",
                      "sharing_hcp_info_company_level": "ON or OFF",
                      "sharing_hcp_infos_bu_level": "ON or OFF",
                      "survery_per_call_quantity": "4"
                 },
                 "questions_list": [{
                     "id": "Q00",
                     "question_name": "Can you please the select product available in a portfolio?",
                     "answer_type": "multiple answer",
                     "answers": {
                          "Q00_a1": "Apidra",
                          "Q00_a3": "Toujeo",
                          "Q00_a2": "Geostar"
                     },
                     "level": "REPS TEAM",
                     "recurence": 0,
                     "speciality_filter": ["Pharmacist"],
                     "expiration_date": null,
                     "weight": 6,
                     "order": 2,
                     "high_priority_order_product" : "HIGH or NULL",
                     "conditions": [],
                 },{
                     "id": "Q07",
                     "question_name": "What is your HCP gender ?",
                     "answer_type": "multiple answer",
                     "answers":{
                          "Q07_a1": "female",
                          "Q07_a2": "male"
                     },
                     "level": "HCP",
                     "recurence": 0,
                     "speciality_filter": ["Cardiologist","Diabetologist"],
                     "expiration_date": null,
                     "weight": 4,
                     "order": 1,
                     "high_priority_order_product" : "HIGH or NULL",
                     "conditions": [],
                 },{
                     "id": "Q09",
                     "question_name": "Is there some print materials from comptetitors?",
                     "answer_type": "multiple answer",
                     "answers":{
                          "Q09_a1": "Yes a lot",
                          "Q09_a3": "Yes a few",
                          "Q09_a2": "Not at all"
                     },
                     "level": "BRAND",
                     "recurence": 4,
                     "speciality_filter": ["Pharmacist"],
                     "expiration_date": null,
                     "weight": 6,
                     "order": 2,
                     "high_priority_order_product" : "HIGH or NULL",
                     "conditions": [],
                 },{
                     "id": "Q10",
                     "question_name": "Brand loyalty ?",
                     "answer_type": "percentage",
                     "answers": [],
                     "level": "BRAND",
                     "recurence": 4,
                     "speciality_filter": ["Pharmacist"],
                     "expiration_date": null,
                     "weight": 6,
                     "order": 2,
                     "high_priority_order_product" : "HIGH or NULL",
                     "conditions": [],
                 }]
             }
         }
}]
